{"nodes": [{"id": "c_web_devlopment_buidwithaihackathon_backend_src_services_n8n_ts", "label": "n8n.ts", "file_type": "code", "source_file": "C:\\Web Devlopment\\BuidWithAiHackathon\\backend\\src\\services\\n8n.ts", "source_location": "L1"}, {"id": "n8n_triggern8nwebhook", "label": "triggerN8NWebhook()", "file_type": "code", "source_file": "C:\\Web Devlopment\\BuidWithAiHackathon\\backend\\src\\services\\n8n.ts", "source_location": "L3"}], "edges": [{"source": "c_web_devlopment_buidwithaihackathon_backend_src_services_n8n_ts", "target": "axios", "relation": "imports_from", "confidence": "EXTRACTED", "source_file": "C:\\Web Devlopment\\BuidWithAiHackathon\\backend\\src\\services\\n8n.ts", "source_location": "L1", "weight": 1.0}, {"source": "c_web_devlopment_buidwithaihackathon_backend_src_services_n8n_ts", "target": "n8n_triggern8nwebhook", "relation": "contains", "confidence": "EXTRACTED", "source_file": "C:\\Web Devlopment\\BuidWithAiHackathon\\backend\\src\\services\\n8n.ts", "source_location": "L3", "weight": 1.0}], "raw_calls": [{"caller_nid": "n8n_triggern8nwebhook", "callee": "log", "source_file": "C:\\Web Devlopment\\BuidWithAiHackathon\\backend\\src\\services\\n8n.ts", "source_location": "L6"}, {"caller_nid": "n8n_triggern8nwebhook", "callee": "stringify", "source_file": "C:\\Web Devlopment\\BuidWithAiHackathon\\backend\\src\\services\\n8n.ts", "source_location": "L6"}, {"caller_nid": "n8n_triggern8nwebhook", "callee": "post", "source_file": "C:\\Web Devlopment\\BuidWithAiHackathon\\backend\\src\\services\\n8n.ts", "source_location": "L11"}, {"caller_nid": "n8n_triggern8nwebhook", "callee": "toISOString", "source_file": "C:\\Web Devlopment\\BuidWithAiHackathon\\backend\\src\\services\\n8n.ts", "source_location": "L13"}, {"caller_nid": "n8n_triggern8nwebhook", "callee": "log", "source_file": "C:\\Web Devlopment\\BuidWithAiHackathon\\backend\\src\\services\\n8n.ts", "source_location": "L16"}, {"caller_nid": "n8n_triggern8nwebhook", "callee": "warn", "source_file": "C:\\Web Devlopment\\BuidWithAiHackathon\\backend\\src\\services\\n8n.ts", "source_location": "L19"}]}